<texts>	<info>			BLOBMINUTE							</info>		
<info>	DIALOG_ID			ENGLISH			FRENCH			EN_COUNT	FR_COUNT	</info>	
<entry id='	PLAY_BTN	'>	<english>	Play	</english>	<french>	Jouer	</french>	<info>	4	5	</info>	</entry>
<entry id='	0-1_SPACE_INTERACT	'>	<english>	Press E to interact	</english>	<french>	Appuyer sur E pour intéragir  	</french>	<info>	20	29	</info>	</entry>
<entry id='	0-1_FIND_KEY	'>	<english>	Find the key !	</english>	<french>	Trouve la clé !  	</french>	<info>	14	15	</info>	</entry>
<entry id='	0-2_SEQ_213	'>	<english>	SEQUENCED lever 2 -> 1 -> 3	</english>	<french>	Levier séquence 2 -> 1 -> 3  	</french>	<info>	29	29	</info>	</entry>
<entry id='	0-2_SPACE_INTERACT	'>	<english>	Press E to interact	</english>	<french>	Appuyer sur E pour intéragir  	</french>	<info>	20	29	</info>	</entry>
<entry id='	0-3_PUSH_CRATE	'>	<english>	Shift + arrow = push	</english>	<french>	Shift + flèche = pousser  	</french>	<info>	22	26	</info>	</entry>
<entry id='	0-3_PULL_CRATE	'>	<english>	Shift + arrow = pull	</english>	<french>	Shift + flèche = tirer  	</french>	<info>	22	24	</info>	</entry>
<entry id='	0-4_TELEPORT	'>	<english>	Press E to teleport	</english>	<french>	Appuyer sur E pour se téléporter  	</french>	<info>	20	34	</info>	</entry>
<entry id='	0-4_RED_TELEPORT	'>	<english>	Red teleport = off	</english>	<french>	Téléporteur rouge = inutilisable	</french>	<info>	19	34	</info>	</entry>
<entry id='	0-5_JUMP	'>	<english>	Jump !!	</english>	<french>	Saute !!	</french>	<info>	7	8	</info>	</entry>
<entry id='	0-5_FALL	'>	<english>	Fall only	</english>	<french>	Juste une chute	</french>	<info>	10	16	</info>	</entry>
<entry id='	0-5_SMALL_JUMP	'>	<english>	Just a small jump	</english>	<french>	Juste un petit saut	</french>	<info>	19	21	</info>	</entry>
<entry id='	0-5_BLOB_IS_COMING	'>	<english>	Blob is coming  !	</english>	<french>	Le Blob arrive maintenant !	</french>	<info>	19	29	</info>	</entry>
<entry id='	0-5_WARNING	'>	<english>	WARNING	</english>	<french>	ATTENTION !	</french>	<info>	7	11	</info>	</entry>
<entry id='	1-1_TUTO	'>	<english>	Alert !/nBlobs have/ninvaded the ship !/nYou have 1 minute/nto find at least/n3 keys to activate/nthe shield generator !	</english>	<french>	Alerte !/nLes Blobs ont envahi le vaisseau !/nTu as 1 minutes pour trouver au moins/n3 clés pour activer le générateur de bouclier !	</french>	<info>	117	135	</info>	</entry>
<entry id='	1-1_GG	'>	<english>	GG !	</english>	<french>	GG !	</french>	<info>	4	4	</info>	</entry>
<entry id='	1-2_BLOB	'>	<english>	Bloooob !	</english>	<french>	Bloooob !	</french>	<info>	9	9	</info>	</entry>
<entry id='	1-3_SEQ312	'>	<english>	3 -> 1 -> 2	</english>	<french>	3 -> 1 -> 2	</french>	<info>	11	11	</info>	</entry>
<entry id='	1-3_RUNNING	'>	<english>	Blob is running out.	</english>	<french>	Blob is running out.	</french>	<info>	22	22	</info>	</entry>
<entry id='	1-4_RUSH	'>	<english>	R/nU/nS/nH	</english>	<french>	V/nI/nT/nE	</french>	<info>	10	10	</info>	</entry>
<entry id='	1-5_LAST	'>	<english>	Last but not least.	</english>	<french>	Le meilleur pour la fin.	</french>	<info>	19	24	</info>	</entry>
<entry id='	1-5_1SEQ123	'>	<english>	1 -> 2 -> 3	</english>	<french>	1 -> 2 -> 3	</french>	<info>	11	11	</info>	</entry>
<entry id='	1-5_2SEQ123	'>	<english>	1 -> 2 -> 3	</english>	<french>	1 -> 2 -> 3	</french>	<info>	11	11	</info>	</entry>
<entry id='	1-5_3SEQ123	'>	<english>	1 -> 2 -> 3	</english>	<french>	1 -> 2 -> 3	</french>	<info>	11	11	</info>	</entry>
<entry id='	1-5_SEQ789	'>	<english>	7 -> 8 -> 9	</english>	<french>	7 -> 8 -> 9	</french>	<info>	11	11	</info>	</entry>
<entry id='	1BOSS_CUBE	'>	<english>	CUBE.	</english>	<french>	CUBE.	</french>	<info>	5	5	</info>	</entry>
<entry id='	1BOSS_SEQ321	'>	<english>	3 -> 2 -> 1	</english>	<french>	3 -> 2 -> 1	</french>	<info>	11	11	</info>	</entry>
<entry id='	1BOSS_TRAP	'>	<english>	TRAP.	</english>	<french>	PIÈGE.	</french>	<info>	5	6	</info>	</entry>
<entry id='	1BOSS_TOLDYOU	'>	<english>	I told you that it was a trap.	</english>	<french>	Je t'avais dit que c'était un piège.	</french>	<info>	30	36	</info>	</entry>
<entry id='	2-1_DoorG	'>	<english>	DoorG	</english>	<french>	Porte G	</french>	<info>	3	4	</info>	</entry>
<entry id='	2-2_DoorG	'>	<english>	DoorG	</english>	<french>	Porte G	</french>	<info>	3	4	</info>	</entry>
<entry id='	2-3_DoorG	'>	<english>	DoorG	</english>	<french>	Porte G	</french>	<info>	3	4	</info>	</entry>
<entry id='	2-4_DoorG	'>	<english>	DoorG	</english>	<french>	Porte G	</french>	<info>	3	4	</info>	</entry>
<entry id='	2-5_DoorG	'>	<english>	DoorG	</english>	<french>	Porte G	</french>	<info>	3	4	</info>	</entry>
<entry id='	2-1_CAB	'>	<english>	CAB	</english>	<french>	TAXI	</french>	<info>	3	4	</info>	</entry>
<entry id='	2-2_SEQ_123	'>	<english>	SEQUENCED Lever 1 -> 2 -> 3	</english>	<french>	Levier séquence 1 -> 2 -> 3	</french>	<info>	29	29	</info>	</entry>
<entry id='	2-1_SEQ_123	'>	<english>	SEQUENCED Lever 1 -> 2 -> 3	</english>	<french>	Levier séquence 1 -> 2 -> 3	</french>	<info>	29	29	</info>	</entry>
<entry id='	2-3_SEQ_123	'>	<english>	SEQUENCED Lever 1 -> 2 -> 3	</english>	<french>	Levier séquence 1 -> 2 -> 3	</french>	<info>	29	29	</info>	</entry>
<entry id='	2-4_SEQ_123	'>	<english>	SEQUENCED Lever 1 -> 2 -> 3	</english>	<french>	Levier séquence 1 -> 2 -> 3	</french>	<info>	29	29	</info>	</entry>
<entry id='	2-5_SEQ_123	'>	<english>	SEQUENCED Lever 1 -> 2 -> 3	</english>	<french>	Levier séquence 1 -> 2 -> 3	</french>	<info>	29	29	</info>	</entry>
<entry id='	2-4_DONT	'>	<english>	Don't kill the blob	</english>	<french>	Ne tue pas le blob.	</french>	<info>	20	21	</info>	</entry>
<entry id='	2-4_RUN	'>	<english>	RUN !	</english>	<french>	Cours !	</french>	<info>	5	7	</info>	</entry>
<entry id='	2-5_SEQ_123	'>	<english>	SEQUENCED Lever 1 -> 2 -> 3	</english>	<french>	Levier séquence 1 -> 2 -> 3	</french>	<info>	29	29	</info>	</entry>
<entry id='	2-5_FAST	'>	<english>	Be fast and smart !	</english>	<french>	Sois rapide et intelligent !	</french>	<info>	21	30	</info>	</entry>
<entry id='	3-1_FAMOUS	'>	<english>	Blob me I'm famous.	</english>	<french>	Blob me I'm famous.	</french>	<info>	20	20	</info>	</entry>
<entry id='	3-2_SEQ_123	'>	<english>	One, two, three go !	</english>	<french>	Et 1 et 2 et 3 !	</french>	<info>	20	16	</info>	</entry>
<entry id='	3-2_CAKE	'>	<english>	The cake is a blob.	</english>	<french>	The cake is a blob.	</french>	<info>	20	20	</info>	</entry>
<entry id='	3-3_PAIN	'>	<english>	No pain, no blob.	</english>	<french>	No pain, no blob.	</french>	<info>	18	18	</info>	</entry>
<entry id='	3-4_NOPE	'>	<english>	Nope.	</english>	<french>	Nope.	</french>	<info>	5	5	</info>	</entry>
<entry id='	3-4_FEEL	'>	<english>	Can you feel the blob tonight ?	</english>	<french>	Can you feel the blob tonight ?	</french>	<info>	33	33	</info>	</entry>
<entry id='	3-4_PRESS	'>	<english>	Pull/nMe &lt;3	</english>	<french>	Actionne/nmoi &lt;3	</french>	<info>	33	33	</info>	</entry>
<entry id='	3-5_SEQ_123	'>	<english>	One Two Three and you're free !	</english>	<french>	Un deux trois. Ouvre toi !	</french>	<info>	22	22	</info>	</entry>
<entry id='	3-5_LOVE	'>	<english>	AND IIIIII WILL ALWAYS BLOB YOUUUUUUU	</english>	<french>	AND IIIIII WILL ALWAYS BLOB YOUUUUUUU	</french>	<info>	39	39	</info>	</entry>
<entry id='	3BOSS_RUN	'>	<english>	RUUUN !	</english>	<french>	COUUURS !	</french>	<info>	5	7	</info>	</entry>
<entry id='	3BOSS_JUMP	'>	<english>	Jump !	</english>	<french>	Saute !	</french>	<info>	6	7	</info>	</entry>
<entry id='	3BOSS_BOUNCE	'>	<english>	Bounce ! Down ! Up !	</english>	<french>	Jump ! Bounce !	</french>	<info>	21	16	</info>	</entry>
<entry id='	3BOSS_ICARUS	'>	<english>	Be careful, Icarus !	</english>	<french>	Gaffe à tes ailes, Icare !	</french>	<info>	20	26	</info>	</entry>
<entry id='	3BOSS_FAST	'>	<english>	SHORTCUT	</english>	<french>	RACCOURCI	</french>	<info>	4	16	</info>	</entry>
<entry id='	3BOSS_SAFE	'>	<english>	SAFE/nWAY	</english>	<french>	SECURITE	</french>	<info>	4	8	</info>	</entry>
<entry id='	3BOSS_LIE	'>	<english>	I lied.	</english>	<french>	J'ai menti.	</french>	<info>	7	11	</info>	</entry>
<entry id='	3BOSS_STEPFAST	'>	<english>	That's one small step  for a blob.	</english>	<french>	Un petit pas pour le blob.	</french>	<info>	37	28	</info>	</entry>
<entry id='	3BOSS_STEPSAFE	'>	<english>	That's one small step for a blob.	</english>	<french>	Un petit pas pour le blob.	</french>	<info>	37	28	</info>	</entry>
<entry id='	3BOSS_LEAP	'>	<english>	                            blob/nOne giant leap for blob/n                            blob	</english>	<french>	                                blob/nUn pas de geant pour blob/n                                 blob 	</french>	<info>	91	103	</info>	</entry>
<entry id='	BACK_BTN	'>	<english>	Back	</english>	<french>	Retour	</french>	<info>	4	6	</info>	</entry>
<entry id='	CHOOSE_LVL	'>	<english>	Choose a level	</english>	<french>	Choisir un niveau	</french>	<info>	14	17	</info>	</entry>
<entry id='	CREDITS_BTN	'>	<english>	Credits	</english>	<french>	Crédits	</french>	<info>	7	7	</info>	</entry>
<entry id='	EXIT_BTN	'>	<english>	Exit	</english>	<french>	Quitter	</french>	<info>	4	7	</info>	</entry>
<entry id='	GFX_CONT	'>	<english>	Adrian Jacques/n	</english>	<french>	Adrian Jacques/nThomas Goffinet	</french>	<info>	16	31	</info>	</entry>
<entry id='	GFX_LABEL	'>	<english>	Graphic art	</english>	<french>	Art graphique	</french>	<info>	11	13	</info>	</entry>
<entry id='	HEADER_TITLE	'>	<english>	The Blob/nMinute	</english>	<french>	The Blob/nMinute	</french>	<info>	16	16	</info>	</entry>
<entry id='	LVL	'>	<english>	One	</english>	<french>	Un	</french>	<info>	3	2	</info>	</entry>
<entry id='	OPTIONS_BTN	'>	<english>	Options	</english>	<french>	Options	</french>	<info>	7	7	</info>	</entry>
<entry id='	PLAY_BTN	'>	<english>	Play	</english>	<french>	Jouer	</french>	<info>	4	5	</info>	</entry>
<entry id='	PROG_CONT	'>	<english>	Bastien Nanceau/nYannick Elahee	</english>	<french>	Bastien Nanceau/nYannick Elahee	</french>	<info>	31	31	</info>	</entry>
<entry id='	PROG_LABEL	'>	<english>	Programming	</english>	<french>	Programmation	</french>	<info>	11	13	</info>	</entry>
<entry id='	SD_CONT	'>	<english>	Paul Lagarrigue	</english>	<french>	Paul Lagarrigue	</french>	<info>	15	15	</info>	</entry>
<entry id='	SD_LABEL	'>	<english>	Sound design	</english>	<french>	Sound design	</french>	<info>	12	12	</info>	</entry>
<entry id='	DESIGN_CONT	'>	<english>	Thomas Goffinet/nJulien Lebon/nBastien Nanceau/nPaul Lagarrigue	</english>	<french>	Thomas Goffinet/nJulien Lebon/nBastien Nanceau/nPaul Lagarrigue	</french>	<info>	63	63	</info>	</entry>
<entry id='	DESIGN_LABEL	'>	<english>	Game and Level design	</english>	<french>	Game and Level design	</french>	<info>	21	21	</info>	</entry>
<entry id='	MUSIC_LABEL	'>	<english>	Music	</english>	<french>	Musique	</french>	<info>	5	7	</info>	</entry>
<entry id='	MUSIC_CONT	'>	<english>	Stéphane Damo	</english>	<french>	Stéphane Damo	</french>	<info>	13	13	</info>	</entry>
<entry id='	VERSION_LABEL	'>	<english>	Alpha/nV2.0	</english>	<french>	Aplha/nV2.0	</french>	<info>	11	11	</info>	</entry>
<entry id='	PAUSE_0	'>	<english>	Pause	</english>	<french>	Pause	</french>	<info>	5	5	</info>	</entry>
<entry id='	PAUSE_1	'>	<english>	Resume	</english>	<french>	Reprendre	</french>	<info>	6	9	</info>	</entry>
<entry id='	PAUSE_2	'>	<english>	---WIP---	</english>	<french>	---WIP---	</french>	<info>	4	11	</info>	</entry>
<entry id='	PAUSE_2-1	'>	<english>	Score Saved	</english>	<french>	Score Sauvegardé	</french>	<info>	11	17	</info>	</entry>
<entry id='	PAUSE_3	'>	<english>	Main Menu	</english>	<french>	Menu Principal	</french>	<info>	9	14	</info>	</entry>
<entry id='	PAUSE_3-1	'>	<english>	Do you really want to go the Main Menu ?/nYour progression in this occurence/nwill be lost.	</english>	<french>	Voulez-vous vraiment aller au Menu Principal ?/nVotre progression dans cette occurence/nsera perdue.	</french>	<info>	91	100	</info>	</entry>
<entry id='	PAUSE_4	'>	<english>	Exit Game	</english>	<french>	Quitter le jeu	</french>	<info>	9	14	</info>	</entry>
<entry id='	PAUSE_4-1	'>	<english>	Do you really want to exit the game ?/nYour progression in this occurence/nwill be lost.	</english>	<french>	Voulez-vous vraiment quitter le jeu ?/nVotre progression dans cette occurence/nsera perdue.	</french>	<info>	88	91	</info>	</entry>
<entry id='	YES	'>	<english>	Yes	</english>	<french>	Oui	</french>	<info>	3	3	</info>	</entry>
<entry id='	NO	'>	<english>	No	</english>	<french>	Non	</french>	<info>	2	3	</info>	</entry>
<entry id='	RESTART_LEVEL	'>	<english>	Restart Level	</english>	<french>	Recommencer	</french>	<info>	13	11	</info>	</entry>
<entry id='	NEXT_LEVEL	'>	<english>	Next Level	</english>	<french>	Continuer	</french>	<info>	10	9	</info>	</entry>
<entry id='	LEVEL_ALL	'>	<english>	Level	</english>	<french>	Niveau	</french>	<info>	5	6	</info>	</entry>
<entry id='	NEW_SCORE	'>	<english>	New Score !	</english>	<french>	Nouveau Score !	</french>	<info>	-11	-15	</info>	</entry>

<entry id='		'>	<english>		</english>	<french>		</french>	<info>	0	0	</info>	</entry>
<entry id='		'>	<english>		</english>	<french>		</french>	<info>	0	0	</info>	</entry>
<entry id='		'>	<english>		</english>	<french>		</french>	<info>	0	0	</info>	</entry>
<entry id='		'>	<english>		</english>	<french>		</french>	<info>	0	0	</info>	</entry>
<entry id='		'>	<english>		</english>	<french>		</french>	<info>	0	0	</info>	</entry>
<entry id='		'>	<english>		</english>	<french>		</french>	<info>	0	0	</info>	</entry>
<entry id='		'>	<english>		</english>	<french>		</french>	<info>	0	0	</info>	</entry>
<entry id='		'>	<english>		</english>	<french>		</french>	<info>	0	0	</info>	</entry>
<entry id='		'>	<english>		</english>	<french>		</french>	<info>	0	0	</info>	</entry>
<entry id='		'>	<english>		</english>	<french>		</french>	<info>	0	0	</info>	</entry>
<entry id='		'>	<english>		</english>	<french>		</french>	<info>	0	0	</info>	</entry>
<entry id='		'>	<english>		</english>	<french>		</french>	<info>	0	0	</info>	</entry>
<entry id='		'>	<english>		</english>	<french>		</french>	<info>	0	0	</info>	</entry>
<entry id='		'>	<english>		</english>	<french>		</french>	<info>	0	0	</info>	</entry>
<entry id='		'>	<english>		</english>	<french>		</french>	<info>	0	0	</info>	</entry>
<entry id='		'>	<english>		</english>	<french>		</french>	<info>	0	0	</info>	</entry>
<entry id='		'>	<english>		</english>	<french>		</french>	<info>	0	0	</info>	</entry>
<entry id='		'>	<english>		</english>	<french>		</french>	<info>	0	0	</info>	</entry>
<entry id='		'>	<english>		</english>	<french>		</french>	<info>	0	0	</info>	</entry>
<entry id='		'>	<english>		</english>	<french>		</french>	<info>	0	0	</info>	</entry>
<entry id='		'>	<english>		</english>	<french>		</french>	<info>	0	0	</info>	</entry>
<entry id='		'>	<english>		</english>	<french>		</french>	<info>	0	0	</info>	</entry>
<entry id='		'>	<english>		</english>	<french>		</french>	<info>	0	0	</info>	</entry>
<entry id='		'>	<english>		</english>	<french>		</french>	<info>	0	0	</info>	</entry>
<entry id='		'>	<english>		</english>	<french>		</french>	<info>	0	0	</info>	</entry>
<entry id='		'>	<english>		</english>	<french>		</french>	<info>	0	0	</info>	</entry>
<entry id='		'>	<english>		</english>	<french>		</french>	<info>	0	0	</info>	</entry>
<entry id='		'>	<english>		</english>	<french>		</french>	<info>	0	0	</info>	</entry>
<entry id='		'>	<english>		</english>	<french>		</french>	<info>	0	0	</info>	</entry>
<entry id='		'>	<english>		</english>	<french>		</french>	<info>	0	0	</info>	</entry>
<entry id='		'>	<english>		</english>	<french>		</french>	<info>	0	0	</info>	</entry>
<entry id='		'>	<english>		</english>	<french>		</french>	<info>	0	0	</info>	</entry>
<entry id='		'>	<english>		</english>	<french>		</french>	<info>	0	0	</info>	</entry>
<entry id='		'>	<english>		</english>	<french>		</french>	<info>	0	0	</info>	</entry>
<entry id='		'>	<english>		</english>	<french>		</french>	<info>	0	0	</info>	</entry>
<entry id='		'>	<english>		</english>	<french>		</french>	<info>	0	0	</info>	</entry>
<entry id='		'>	<english>		</english>	<french>		</french>	<info>	0	0	</info>	</entry>
<entry id='		'>	<english>		</english>	<french>		</french>	<info>	0	0	</info>	</entry>
<entry id='		'>	<english>		</english>	<french>		</french>	<info>	0	0	</info>	</entry>
<entry id='		'>	<english>		</english>	<french>		</french>	<info>	0	0	</info>	</entry>
<entry id='		'>	<english>		</english>	<french>		</french>	<info>	0	0	</info>	</entry>
<entry id='		'>	<english>		</english>	<french>		</french>	<info>	0	0	</info>	</entry>
<entry id='		'>	<english>		</english>	<french>		</french>	<info>	0	0	</info>	</entry>
<entry id='		'>	<english>		</english>	<french>		</french>	<info>	0	0	</info>	</entry>
<entry id='		'>	<english>		</english>	<french>		</french>	<info>	0	0	</info>	</entry>
<entry id='		'>	<english>		</english>	<french>		</french>	<info>	0	0	</info>	</entry>
<entry id='		'>	<english>		</english>	<french>		</french>	<info>	0	0	</info>	</entry>
<entry id='		'>	<english>		</english>	<french>		</french>	<info>	0	0	</info>	</entry>
<entry id='		'>	<english>		</english>	<french>		</french>	<info>	0	0	</info>	</entry>
<entry id='		'>	<english>		</english>	<french>		</french>	<info>	0	0	</info>	</entry>
<entry id='		'>	<english>		</english>	<french>		</french>	<info>	0	0	</info>	</entry>
<entry id='		'>	<english>		</english>	<french>		</french>	<info>	0	0	</info>	</entry>
<entry id='		'>	<english>		</english>	<french>		</french>	<info>	0	0	</info>	</entry>
<entry id='		'>	<english>		</english>	<french>		</french>	<info>	0	0	</info>	</entry>
</texts>													